Workbook

Sheet Assumptions
A1: Followthroo — Cost & Revenue Model: Assumptions
A3: FX rate (₹ per $1) | B3: 87
A5: Tier pricing (₹ / user / month)
A6: Startup | B6: 999
A7: Growth | B7: 2499
A8: Enterprise | B8: 4999
A10: AI cost per seat ($ / user / month — modeled, not measured; replace with real token usage once live)
A11: Startup (Basic AI) | B11: 2.5
A12: Growth (Advanced AI) | B12: 6
A13: Enterprise (Custom AI) | B13: 9
A15: Blended plan mix (recommended funnel — Growth as hero tier)
A16: Startup % | B16: 0.2
A17: Growth % | B17: 0.7
A18: Enterprise % | B18: 0.1
A20: Blended ARPU (₹ / user / month) | B20: =B16*B6+B17*B7+B18*B8
A21: Blended AI cost / seat ($ / user / month) | B21: =B16*B11+B17*B12+B18*B13
A23: Payment processing (Razorpay, % of revenue — domestic card/UPI + subscription fee, blended) | B23: 0.03
A25: Fixed platform infra by scale ($/month — Vercel + Supabase + Upstash Redis/QStash on Pay-as-you-go)
A26: People (seats) | B26: Vercel ($) | C26: Supabase ($) | D26: Upstash ($)
A27: 10 | B27: 20 | C27: 25 | D27: 2
A28: 25 | B28: 20 | C28: 25 | D28: 4
A29: 50 | B29: 20 | C29: 30 | D29: 7
A30: 100 | B30: 20 | C30: 40 | D30: 13
A31: 250 | B31: 40 | C31: 75 | D31: 30
A32: 500 | B32: 60 | C32: 140 | D32: 58
A33: 1000 | B33: 100 | C33: 230 | D33: 105
A35: Notes:
A36: • AI cost is a bottom-up model (Claude Opus 5 agent-loop invocations + Claude Haiku 4.5 reply classifier), not measured usage — the single biggest swing factor in this workbook.
A37: • Infra figures assume Pay-as-you-go on Upstash (Redis + QStash) and a lean team (1–4 Vercel seats as headcount grows with scale), not a fixed team-seat count.
A38: • Payment processing modeled as Razorpay (India-first): ~2% + GST domestic + ~1% subscription fee → blended ~3% of revenue.
A39: • Infra is modeled as a function of total seats regardless of plan mix, as a simplification — a Growth/Enterprise-heavy base would run somewhat higher due to more automation activity.
A40: • All dollar figures pulled from live pricing research on 2026-08-14 — re-verify before using for real financial planning; these rates drift.
A41: • Change any yellow input cell (FX rate, tier prices, AI $/seat, plan mix, payment %) and every scenario sheet recalculates automatically.

Sheet Blended Mix (Recommended)
A1: Followthroo — Blended Mix (Recommended)
A2: Assumes the recommended funnel mix: 20% Startup / 70% Growth / 10% Enterprise seats — the primary scenario to plan around.
A4: People (seats) | B4: Revenue (₹/mo) | C4: Vercel ($) | D4: Supabase ($) | E4: Upstash ($) | F4: Infra Subtotal (₹/mo) | G4: AI Cost (₹/mo) | H4: Payment Processing (₹/mo) | I4: Total Cost (₹/mo) | J4: Gross Margin (₹/mo) | K4: Gross Margin (%)
A5: =Assumptions!A27 | B5: =A5*Assumptions!$B$20 | C5: =Assumptions!B27 | D5: =Assumptions!C27 | E5: =Assumptions!D27 | F5: =(C5+D5+E5)*Assumptions!$B$3 | G5: =A5*Assumptions!$B$21*Assumptions!$B$3 | H5: =B5*Assumptions!$B$23 | I5: =F5+G5+H5 | J5: =B5-I5 | K5: =J5/B5
A6: =Assumptions!A28 | B6: =A6*Assumptions!$B$20 | C6: =Assumptions!B28 | D6: =Assumptions!C28 | E6: =Assumptions!D28 | F6: =(C6+D6+E6)*Assumptions!$B$3 | G6: =A6*Assumptions!$B$21*Assumptions!$B$3 | H6: =B6*Assumptions!$B$23 | I6: =F6+G6+H6 | J6: =B6-I6 | K6: =J6/B6
A7: =Assumptions!A29 | B7: =A7*Assumptions!$B$20 | C7: =Assumptions!B29 | D7: =Assumptions!C29 | E7: =Assumptions!D29 | F7: =(C7+D7+E7)*Assumptions!$B$3 | G7: =A7*Assumptions!$B$21*Assumptions!$B$3 | H7: =B7*Assumptions!$B$23 | I7: =F7+G7+H7 | J7: =B7-I7 | K7: =J7/B7
A8: =Assumptions!A30 | B8: =A8*Assumptions!$B$20 | C8: =Assumptions!B30 | D8: =Assumptions!C30 | E8: =Assumptions!D30 | F8: =(C8+D8+E8)*Assumptions!$B$3 | G8: =A8*Assumptions!$B$21*Assumptions!$B$3 | H8: =B8*Assumptions!$B$23 | I8: =F8+G8+H8 | J8: =B8-I8 | K8: =J8/B8
A9: =Assumptions!A31 | B9: =A9*Assumptions!$B$20 | C9: =Assumptions!B31 | D9: =Assumptions!C31 | E9: =Assumptions!D31 | F9: =(C9+D9+E9)*Assumptions!$B$3 | G9: =A9*Assumptions!$B$21*Assumptions!$B$3 | H9: =B9*Assumptions!$B$23 | I9: =F9+G9+H9 | J9: =B9-I9 | K9: =J9/B9
A10: =Assumptions!A32 | B10: =A10*Assumptions!$B$20 | C10: =Assumptions!B32 | D10: =Assumptions!C32 | E10: =Assumptions!D32 | F10: =(C10+D10+E10)*Assumptions!$B$3 | G10: =A10*Assumptions!$B$21*Assumptions!$B$3 | H10: =B10*Assumptions!$B$23 | I10: =F10+G10+H10 | J10: =B10-I10 | K10: =J10/B10
A11: =Assumptions!A33 | B11: =A11*Assumptions!$B$20 | C11: =Assumptions!B33 | D11: =Assumptions!C33 | E11: =Assumptions!D33 | F11: =(C11+D11+E11)*Assumptions!$B$3 | G11: =A11*Assumptions!$B$21*Assumptions!$B$3 | H11: =B11*Assumptions!$B$23 | I11: =F11+G11+H11 | J11: =B11-I11 | K11: =J11/B11

Sheet All Startup
A1: Followthroo — All Startup
A2: Reference scenario: every seat on the ₹999 Startup plan (floor case — worst realistic margin).
A4: People (seats) | B4: Revenue (₹/mo) | C4: Vercel ($) | D4: Supabase ($) | E4: Upstash ($) | F4: Infra Subtotal (₹/mo) | G4: AI Cost (₹/mo) | H4: Payment Processing (₹/mo) | I4: Total Cost (₹/mo) | J4: Gross Margin (₹/mo) | K4: Gross Margin (%)
A5: =Assumptions!A27 | B5: =A5*Assumptions!$B$6 | C5: =Assumptions!B27 | D5: =Assumptions!C27 | E5: =Assumptions!D27 | F5: =(C5+D5+E5)*Assumptions!$B$3 | G5: =A5*Assumptions!$B$11*Assumptions!$B$3 | H5: =B5*Assumptions!$B$23 | I5: =F5+G5+H5 | J5: =B5-I5 | K5: =J5/B5
A6: =Assumptions!A28 | B6: =A6*Assumptions!$B$6 | C6: =Assumptions!B28 | D6: =Assumptions!C28 | E6: =Assumptions!D28 | F6: =(C6+D6+E6)*Assumptions!$B$3 | G6: =A6*Assumptions!$B$11*Assumptions!$B$3 | H6: =B6*Assumptions!$B$23 | I6: =F6+G6+H6 | J6: =B6-I6 | K6: =J6/B6
A7: =Assumptions!A29 | B7: =A7*Assumptions!$B$6 | C7: =Assumptions!B29 | D7: =Assumptions!C29 | E7: =Assumptions!D29 | F7: =(C7+D7+E7)*Assumptions!$B$3 | G7: =A7*Assumptions!$B$11*Assumptions!$B$3 | H7: =B7*Assumptions!$B$23 | I7: =F7+G7+H7 | J7: =B7-I7 | K7: =J7/B7
A8: =Assumptions!A30 | B8: =A8*Assumptions!$B$6 | C8: =Assumptions!B30 | D8: =Assumptions!C30 | E8: =Assumptions!D30 | F8: =(C8+D8+E8)*Assumptions!$B$3 | G8: =A8*Assumptions!$B$11*Assumptions!$B$3 | H8: =B8*Assumptions!$B$23 | I8: =F8+G8+H8 | J8: =B8-I8 | K8: =J8/B8
A9: =Assumptions!A31 | B9: =A9*Assumptions!$B$6 | C9: =Assumptions!B31 | D9: =Assumptions!C31 | E9: =Assumptions!D31 | F9: =(C9+D9+E9)*Assumptions!$B$3 | G9: =A9*Assumptions!$B$11*Assumptions!$B$3 | H9: =B9*Assumptions!$B$23 | I9: =F9+G9+H9 | J9: =B9-I9 | K9: =J9/B9
A10: =Assumptions!A32 | B10: =A10*Assumptions!$B$6 | C10: =Assumptions!B32 | D10: =Assumptions!C32 | E10: =Assumptions!D32 | F10: =(C10+D10+E10)*Assumptions!$B$3 | G10: =A10*Assumptions!$B$11*Assumptions!$B$3 | H10: =B10*Assumptions!$B$23 | I10: =F10+G10+H10 | J10: =B10-I10 | K10: =J10/B10
A11: =Assumptions!A33 | B11: =A11*Assumptions!$B$6 | C11: =Assumptions!B33 | D11: =Assumptions!C33 | E11: =Assumptions!D33 | F11: =(C11+D11+E11)*Assumptions!$B$3 | G11: =A11*Assumptions!$B$11*Assumptions!$B$3 | H11: =B11*Assumptions!$B$23 | I11: =F11+G11+H11 | J11: =B11-I11 | K11: =J11/B11

Sheet All Growth
A1: Followthroo — All Growth
A2: Reference scenario: every seat on the ₹2,499 Growth (hero) plan.
A4: People (seats) | B4: Revenue (₹/mo) | C4: Vercel ($) | D4: Supabase ($) | E4: Upstash ($) | F4: Infra Subtotal (₹/mo) | G4: AI Cost (₹/mo) | H4: Payment Processing (₹/mo) | I4: Total Cost (₹/mo) | J4: Gross Margin (₹/mo) | K4: Gross Margin (%)
A5: =Assumptions!A27 | B5: =A5*Assumptions!$B$7 | C5: =Assumptions!B27 | D5: =Assumptions!C27 | E5: =Assumptions!D27 | F5: =(C5+D5+E5)*Assumptions!$B$3 | G5: =A5*Assumptions!$B$12*Assumptions!$B$3 | H5: =B5*Assumptions!$B$23 | I5: =F5+G5+H5 | J5: =B5-I5 | K5: =J5/B5
A6: =Assumptions!A28 | B6: =A6*Assumptions!$B$7 | C6: =Assumptions!B28 | D6: =Assumptions!C28 | E6: =Assumptions!D28 | F6: =(C6+D6+E6)*Assumptions!$B$3 | G6: =A6*Assumptions!$B$12*Assumptions!$B$3 | H6: =B6*Assumptions!$B$23 | I6: =F6+G6+H6 | J6: =B6-I6 | K6: =J6/B6
A7: =Assumptions!A29 | B7: =A7*Assumptions!$B$7 | C7: =Assumptions!B29 | D7: =Assumptions!C29 | E7: =Assumptions!D29 | F7: =(C7+D7+E7)*Assumptions!$B$3 | G7: =A7*Assumptions!$B$12*Assumptions!$B$3 | H7: =B7*Assumptions!$B$23 | I7: =F7+G7+H7 | J7: =B7-I7 | K7: =J7/B7
A8: =Assumptions!A30 | B8: =A8*Assumptions!$B$7 | C8: =Assumptions!B30 | D8: =Assumptions!C30 | E8: =Assumptions!D30 | F8: =(C8+D8+E8)*Assumptions!$B$3 | G8: =A8*Assumptions!$B$12*Assumptions!$B$3 | H8: =B8*Assumptions!$B$23 | I8: =F8+G8+H8 | J8: =B8-I8 | K8: =J8/B8
A9: =Assumptions!A31 | B9: =A9*Assumptions!$B$7 | C9: =Assumptions!B31 | D9: =Assumptions!C31 | E9: =Assumptions!D31 | F9: =(C9+D9+E9)*Assumptions!$B$3 | G9: =A9*Assumptions!$B$12*Assumptions!$B$3 | H9: =B9*Assumptions!$B$23 | I9: =F9+G9+H9 | J9: =B9-I9 | K9: =J9/B9
A10: =Assumptions!A32 | B10: =A10*Assumptions!$B$7 | C10: =Assumptions!B32 | D10: =Assumptions!C32 | E10: =Assumptions!D32 | F10: =(C10+D10+E10)*Assumptions!$B$3 | G10: =A10*Assumptions!$B$12*Assumptions!$B$3 | H10: =B10*Assumptions!$B$23 | I10: =F10+G10+H10 | J10: =B10-I10 | K10: =J10/B10
A11: =Assumptions!A33 | B11: =A11*Assumptions!$B$7 | C11: =Assumptions!B33 | D11: =Assumptions!C33 | E11: =Assumptions!D33 | F11: =(C11+D11+E11)*Assumptions!$B$3 | G11: =A11*Assumptions!$B$12*Assumptions!$B$3 | H11: =B11*Assumptions!$B$23 | I11: =F11+G11+H11 | J11: =B11-I11 | K11: =J11/B11

Sheet All Enterprise
A1: Followthroo — All Enterprise
A2: Reference scenario: every seat on the ₹4,999 Enterprise plan (ceiling case — best realistic margin).
A4: People (seats) | B4: Revenue (₹/mo) | C4: Vercel ($) | D4: Supabase ($) | E4: Upstash ($) | F4: Infra Subtotal (₹/mo) | G4: AI Cost (₹/mo) | H4: Payment Processing (₹/mo) | I4: Total Cost (₹/mo) | J4: Gross Margin (₹/mo) | K4: Gross Margin (%)
A5: =Assumptions!A27 | B5: =A5*Assumptions!$B$8 | C5: =Assumptions!B27 | D5: =Assumptions!C27 | E5: =Assumptions!D27 | F5: =(C5+D5+E5)*Assumptions!$B$3 | G5: =A5*Assumptions!$B$13*Assumptions!$B$3 | H5: =B5*Assumptions!$B$23 | I5: =F5+G5+H5 | J5: =B5-I5 | K5: =J5/B5
A6: =Assumptions!A28 | B6: =A6*Assumptions!$B$8 | C6: =Assumptions!B28 | D6: =Assumptions!C28 | E6: =Assumptions!D28 | F6: =(C6+D6+E6)*Assumptions!$B$3 | G6: =A6*Assumptions!$B$13*Assumptions!$B$3 | H6: =B6*Assumptions!$B$23 | I6: =F6+G6+H6 | J6: =B6-I6 | K6: =J6/B6
A7: =Assumptions!A29 | B7: =A7*Assumptions!$B$8 | C7: =Assumptions!B29 | D7: =Assumptions!C29 | E7: =Assumptions!D29 | F7: =(C7+D7+E7)*Assumptions!$B$3 | G7: =A7*Assumptions!$B$13*Assumptions!$B$3 | H7: =B7*Assumptions!$B$23 | I7: =F7+G7+H7 | J7: =B7-I7 | K7: =J7/B7
A8: =Assumptions!A30 | B8: =A8*Assumptions!$B$8 | C8: =Assumptions!B30 | D8: =Assumptions!C30 | E8: =Assumptions!D30 | F8: =(C8+D8+E8)*Assumptions!$B$3 | G8: =A8*Assumptions!$B$13*Assumptions!$B$3 | H8: =B8*Assumptions!$B$23 | I8: =F8+G8+H8 | J8: =B8-I8 | K8: =J8/B8
A9: =Assumptions!A31 | B9: =A9*Assumptions!$B$8 | C9: =Assumptions!B31 | D9: =Assumptions!C31 | E9: =Assumptions!D31 | F9: =(C9+D9+E9)*Assumptions!$B$3 | G9: =A9*Assumptions!$B$13*Assumptions!$B$3 | H9: =B9*Assumptions!$B$23 | I9: =F9+G9+H9 | J9: =B9-I9 | K9: =J9/B9
A10: =Assumptions!A32 | B10: =A10*Assumptions!$B$8 | C10: =Assumptions!B32 | D10: =Assumptions!C32 | E10: =Assumptions!D32 | F10: =(C10+D10+E10)*Assumptions!$B$3 | G10: =A10*Assumptions!$B$13*Assumptions!$B$3 | H10: =B10*Assumptions!$B$23 | I10: =F10+G10+H10 | J10: =B10-I10 | K10: =J10/B10
A11: =Assumptions!A33 | B11: =A11*Assumptions!$B$8 | C11: =Assumptions!B33 | D11: =Assumptions!C33 | E11: =Assumptions!D33 | F11: =(C11+D11+E11)*Assumptions!$B$3 | G11: =A11*Assumptions!$B$13*Assumptions!$B$3 | H11: =B11*Assumptions!$B$23 | I11: =F11+G11+H11 | J11: =B11-I11 | K11: =J11/B11
